README.txt
setup.py
pylons_sandbox/__init__.py
pylons_sandbox/egg.py
pylons_sandbox.egg-info/PKG-INFO
pylons_sandbox.egg-info/SOURCES.txt
pylons_sandbox.egg-info/dependency_links.txt
pylons_sandbox.egg-info/entry_points.txt
pylons_sandbox.egg-info/requires.txt
pylons_sandbox.egg-info/top_level.txt
