Metadata-Version: 1.0
Name: pylons-sandbox
Version: 0.1.0
Summary: An experimental Buildout recipe backwards-compatible with zc.buildout.egg but with extra features for Pylons users.
Home-page: UNKNOWN
Author: James Gardner
Author-email: james at pythonweb dot org
License: UNKNOWN
Platform: UNKNOWN
Classifier: Framework :: Buildout
Classifier: Development Status :: 3 - Alpha
Classifier: Intended Audience :: Developers
Classifier: License :: OSI Approved :: Zope Public License
Classifier: Topic :: Software Development :: Build Tools
Classifier: Topic :: Software Development :: Libraries :: Python Modules
